userpaths/__init__.py
userpaths/__main__.py
userpaths/unix.py
userpaths/windows.py
userpaths-0.1.3.dist-info/LICENSE
userpaths-0.1.3.dist-info/METADATA
userpaths-0.1.3.dist-info/WHEEL
userpaths-0.1.3.dist-info/top_level.txt
userpaths-0.1.3.dist-info/RECORD
