Metadata-Version: 2.1
Name: userpaths
Version: 0.1.3
Summary: Cross-platform access to a user's special folders
Home-page: https://github.com/bmjcode/userpaths
Author: Benjamin Johnson
Author-email: bmjcode@gmail.com
License: UNKNOWN
Platform: UNKNOWN
Classifier: Development Status :: 4 - Beta
Classifier: Programming Language :: Python :: 2
Classifier: Programming Language :: Python :: 3
Classifier: License :: OSI Approved :: MIT License
Classifier: Operating System :: OS Independent
